nonebot_plugin_nikke-0.1.0.post4.dist-info/METADATA
nonebot_plugin_nikke-0.1.0.post4.dist-info/WHEEL
nonebot_plugin_nikke-0.1.0.post4.dist-info/licenses/LICENSE
nonebot_plugin_nikke/__init__.py
nonebot_plugin_nikke/commands/__init__.py
nonebot_plugin_nikke/commands/character_picture.py
nonebot_plugin_nikke/commands/character_rating.py
nonebot_plugin_nikke/json/character_data.json
nonebot_plugin_nikke/json/character_rating.json
nonebot_plugin_nikke-0.1.0.post4.dist-info/RECORD
