Metadata-Version: 2.1
Name: nonebot-plugin-nikke
Version: 0.1.0.post4
Summary: 胜利女神：妮姬nonebot2插件
Keywords: nikke nonebot nonebot2 bot qq
Home-page: https://github.com/Perseus037/nonebot_plugin_nikke/
Author-Email: Perseus037 <1209228678@qq.com>
License: MIT
Classifier: Natural Language :: Chinese (Simplified)
Classifier: Topic :: Communications
Classifier: Topic :: Communications :: Chat
Classifier: Topic :: Games/Entertainment
Classifier: Topic :: Internet
Classifier: Topic :: Internet :: WWW/HTTP
Classifier: Topic :: Internet :: WWW/HTTP :: Dynamic Content
Project-URL: Homepage, https://github.com/Perseus037/nonebot_plugin_nikke/
Requires-Python: <4.0,>=3.8
Requires-Dist: nonebot2>=2.1.1
Requires-Dist: nonebot-adapter-onebot>=2.3.1
Requires-Dist: httpx>=0.21.1
Requires-Dist: nonebot-plugin-PicMenu>=0.2; extra == "menu"
Provides-Extra: menu
